openapiopenai/__init__.py
openapiopenai/api_client.py
openapiopenai/api_response.py
openapiopenai/configuration.py
openapiopenai/exceptions.py
openapiopenai/py.typed
openapiopenai/rest.py
openapiopenai/api/__init__.py
openapiopenai/api/assistants_api.py
openapiopenai/api/audio_api.py
openapiopenai/api/audit_logs_api.py
openapiopenai/api/batch_api.py
openapiopenai/api/chat_api.py
openapiopenai/api/completions_api.py
openapiopenai/api/default_api.py
openapiopenai/api/embeddings_api.py
openapiopenai/api/files_api.py
openapiopenai/api/fine_tuning_api.py
openapiopenai/api/images_api.py
openapiopenai/api/invites_api.py
openapiopenai/api/models_api.py
openapiopenai/api/moderations_api.py
openapiopenai/api/projects_api.py
openapiopenai/api/realtime_api.py
openapiopenai/api/uploads_api.py
openapiopenai/api/usage_api.py
openapiopenai/api/users_api.py
openapiopenai/api/vector_stores_api.py
openapiopenai/models/__init__.py
openapiopenai/models/admin_api_key.py
openapiopenai/models/admin_api_key_owner.py
openapiopenai/models/admin_api_keys_create_request.py
openapiopenai/models/admin_api_keys_delete200_response.py
openapiopenai/models/api_key_list.py
openapiopenai/models/array_of_content_parts_inner.py
openapiopenai/models/assistant_object.py
openapiopenai/models/assistant_object_tool_resources.py
openapiopenai/models/assistant_object_tool_resources_code_interpreter.py
openapiopenai/models/assistant_object_tool_resources_file_search.py
openapiopenai/models/assistant_object_tools_inner.py
openapiopenai/models/assistant_stream_event.py
openapiopenai/models/assistant_tools_code.py
openapiopenai/models/assistant_tools_file_search.py
openapiopenai/models/assistant_tools_file_search_file_search.py
openapiopenai/models/assistant_tools_file_search_type_only.py
openapiopenai/models/assistant_tools_function.py
openapiopenai/models/assistants_api_response_format_option.py
openapiopenai/models/assistants_api_tool_choice_option.py
openapiopenai/models/assistants_named_tool_choice.py
openapiopenai-1.2.0.dist-info/METADATA
openapiopenai-1.2.0.dist-info/WHEEL
openapiopenai-1.2.0.dist-info/top_level.txt
openapiopenai-1.2.0.dist-info/RECORD
