Metadata-Version: 2.4
Name: openapiopenai
Version: 1.2.0
Summary: OpenAI API
Home-page: https://github.com/oapicf/openapi-openai
Author: Cliffano Subagio
Author-email: Cliffano Subagio <blah+oapicf@cliffano.com>
License: MIT
Project-URL: Repository, https://github.com/oapicf/openapi-openai
Keywords: OpenAPI,OpenAPI-Generator,OpenAI API
Requires-Python: >=3.9
Requires-Dist: urllib3<3.0.0,>=2.1.0
Requires-Dist: python-dateutil>=2.8.2
Requires-Dist: pydantic>=2
Requires-Dist: typing-extensions>=4.7.1
Dynamic: author
Dynamic: home-page
